nyxus/__init__.py
nyxus/_version.py
nyxus/backend.cpython-310-x86_64-linux-gnu.so
nyxus/functions.py
nyxus/nyxus.py
nyxus.libs/libarrow-3d9fcb50.so.2000.0.0
nyxus.libs/libblosc-b136fe6a.so.1.21.6
nyxus.libs/libcmr-edc65e30.so.19.3.6.9
nyxus.libs/libcrypto-bfee2032.so.1.1.1k
nyxus.libs/libdcmdata-0b873e36.so.19.3.6.9
nyxus.libs/libdcmdsig-fc04d111.so.19.3.6.9
nyxus.libs/libdcmect-55896688.so.19.3.6.9
nyxus.libs/libdcmfg-0c9964e7.so.19.3.6.9
nyxus.libs/libdcmimage-1545f22b.so.19.3.6.9
nyxus.libs/libdcmimgle-80bc84a3.so.19.3.6.9
nyxus.libs/libdcmiod-59168f30.so.19.3.6.9
nyxus.libs/libdcmjpeg-0205e04e.so.19.3.6.9
nyxus.libs/libdcmjpls-f2ccba01.so.19.3.6.9
nyxus.libs/libdcmnet-16d84e8c.so.19.3.6.9
nyxus.libs/libdcmpmap-158643c0.so.19.3.6.9
nyxus.libs/libdcmpstat-067a2963.so.19.3.6.9
nyxus.libs/libdcmqrdb-869b9851.so.19.3.6.9
nyxus.libs/libdcmrt-a9d88732.so.19.3.6.9
nyxus.libs/libdcmseg-c20e730d.so.19.3.6.9
nyxus.libs/libdcmsr-9af3289f.so.19.3.6.9
nyxus.libs/libdcmtkcharls-9713e572.so.19.3.6.9
nyxus.libs/libdcmtls-2e67b71b.so.19.3.6.9
nyxus.libs/libdcmtract-5979b7f0.so.19.3.6.9
nyxus.libs/libdcmwlm-6c98cf58.so.19.3.6.9
nyxus.libs/libdcmxml-5e7727d1.so.19.3.6.9
nyxus.libs/libdeflate-5293de93.so.0
nyxus.libs/libfmjpeg2k-a9bc1daf.so.1.0.3
nyxus.libs/libi2d-0a36cebe.so.19.3.6.9
nyxus.libs/libijg12-1fc682c6.so.19.3.6.9
nyxus.libs/libijg16-ca173b7a.so.19.3.6.9
nyxus.libs/libijg8-017cf1e9.so.19.3.6.9
nyxus.libs/libjpeg-089d6684.so.62.4.0
nyxus.libs/liboficonv-c31b88ab.so.19.3.6.9
nyxus.libs/liboflog-8d77b60a.so.19.3.6.9
nyxus.libs/libofstd-3ab520b3.so.19.3.6.9
nyxus.libs/libopenjp2-b488e02a.so.2.5.0
nyxus.libs/libparquet-0d0b2677.so.2000.0.0
nyxus.libs/libpng16-7fac9456.so.16.53.0
nyxus.libs/libssl-658e53cd.so.1.1.1k
nyxus.libs/libtiff-24535aaa.so.6.1.0
nyxus-0.10.0.dist-info/METADATA
nyxus-0.10.0.dist-info/WHEEL
nyxus-0.10.0.dist-info/top_level.txt
nyxus-0.10.0.dist-info/RECORD
nyxus-0.10.0.dist-info/licenses/LICENSE
nyxus-0.10.0.dist-info/sboms/auditwheel.cdx.json
