Metadata-Version: 2.4
Name: nyxus
Version: 0.10.0
Summary: Scalable library for calculating features from intensity-label image data
Home-page: https://github.com/PolusAI/nyxus
Author: Andriy Kharchenko
Author-email: andriy.kharchenko@axleinfo.com
Requires-Python: >=3.8
License-File: LICENSE
Requires-Dist: numpy
Requires-Dist: pandas
Dynamic: author
Dynamic: author-email
Dynamic: description
Dynamic: description-content-type
Dynamic: home-page
Dynamic: license-file
Dynamic: requires-dist
Dynamic: requires-python
Dynamic: summary
